<?xml version="1.0" encoding="UTF-8"?>
<metadata xml:lang="en"><Esri><CreaDate>20220217</CreaDate><CreaTime>10165700</CreaTime><ArcGISFormat>1.0</ArcGISFormat><SyncOnce>TRUE</SyncOnce><DataProperties><lineage><Process ToolSource="c:\program files\arcgis\pro\Resources\ArcToolbox\Toolboxes\Data Management Tools.tbx\Rename" Date="20220217" Time="101651">Rename "C:\Users\belsp\Google Drive\Academia\Australian National University\Projects\Eastern quoll\Spatial\Mapping\Data\MFWS\Tracks\tracks.shp" "C:\Users\belsp\Google Drive\Academia\Australian National University\Projects\Eastern quoll\Spatial\Mapping\Data\MFWS\Tracks\MFWS_tracks.shp" ShapeFile</Process><Process ToolSource="c:\program files\arcgis\pro\Resources\ArcToolbox\Toolboxes\Data Management Tools.tbx\Copy" Date="20220217" Time="101657">Copy "C:\Users\belsp\Google Drive\Academia\Australian National University\Projects\Eastern quoll\Spatial\Mapping\Data\MFWS\Tracks\MFWS_tracks.shp" "C:\Users\belsp\Google Drive\Academia\Australian National University\Projects\Eastern quoll\Spatial\Mapping\Data\MFWS\MFWS_tracks.shp" Shapefile #</Process></lineage><itemProps><itemLocation><linkage Sync="TRUE">file://\\fses52-003\mulligans\MULLIGANS-GOOROOYARROO\DATA\GIS\Features\MFWS_tracks</linkage><protocol Sync="TRUE">Local Area Network</protocol></itemLocation></itemProps><copyHistory><copy source="Z:\MULLIGANS-GOOROOYARROO\DATA\GIS\Eastern_quoll\MFGO\MFWS_tracks" dest="\\fses52-003\mulligans\MULLIGANS-GOOROOYARROO\DATA\GIS\Features\MFWS_tracks" date="20220222" time="16383000"></copy></copyHistory></DataProperties></Esri></metadata>
